<annotation>
  <folder>images/kaggle_fire/fire_images/601_650</folder>
  <filename>fire.628.png</filename>
  <segmented>0</segmented>
  <size>
    <width>1024</width>
    <height>725</height>
    <depth>3</depth>
  </size>
  <object>
    <name>fire</name>
    <pose>Unspecified</pose>
    <truncated>0</truncated>
    <difficult>0</difficult>
    <bndbox>
      <xmin>3</xmin>
      <ymin>78</ymin>
      <xmax>830</xmax>
      <ymax>329</ymax>
    </bndbox>
  </object>
  <object>
    <name>fire</name>
    <pose>Unspecified</pose>
    <truncated>0</truncated>
    <difficult>0</difficult>
    <bndbox>
      <xmin>1</xmin>
      <ymin>351</ymin>
      <xmax>169</xmax>
      <ymax>618</ymax>
    </bndbox>
  </object>
</annotation>
