<annotation>
  <folder>images/kaggle_fire/fire_images/51_100</folder>
  <filename>fire.67.png</filename>
  <segmented>0</segmented>
  <size>
    <width>900</width>
    <height>675</height>
    <depth>3</depth>
  </size>
  <object>
    <name>fire</name>
    <pose>Unspecified</pose>
    <truncated>0</truncated>
    <difficult>0</difficult>
    <bndbox>
      <xmin>9</xmin>
      <ymin>309</ymin>
      <xmax>873</xmax>
      <ymax>538</ymax>
    </bndbox>
  </object>
  <object>
    <name>fire</name>
    <pose>Unspecified</pose>
    <truncated>0</truncated>
    <difficult>0</difficult>
    <bndbox>
      <xmin>257</xmin>
      <ymin>571</ymin>
      <xmax>738</xmax>
      <ymax>670</ymax>
    </bndbox>
  </object>
  <object>
    <name>fire</name>
    <pose>Unspecified</pose>
    <truncated>0</truncated>
    <difficult>0</difficult>
    <bndbox>
      <xmin>276</xmin>
      <ymin>63</ymin>
      <xmax>356</xmax>
      <ymax>352</ymax>
    </bndbox>
  </object>
  <object>
    <name>fire</name>
    <pose>Unspecified</pose>
    <truncated>0</truncated>
    <difficult>0</difficult>
    <bndbox>
      <xmin>671</xmin>
      <ymin>88</ymin>
      <xmax>730</xmax>
      <ymax>372</ymax>
    </bndbox>
  </object>
</annotation>
