<annotation>
  <folder>images/kaggle_fire/fire_images/651_700</folder>
  <filename>fire.661.png</filename>
  <segmented>0</segmented>
  <size>
    <width>1023</width>
    <height>575</height>
    <depth>3</depth>
  </size>
  <object>
    <name>fire</name>
    <pose>Unspecified</pose>
    <truncated>0</truncated>
    <difficult>0</difficult>
    <bndbox>
      <xmin>83</xmin>
      <ymin>7</ymin>
      <xmax>332</xmax>
      <ymax>191</ymax>
    </bndbox>
  </object>
  <object>
    <name>fire</name>
    <pose>Unspecified</pose>
    <truncated>0</truncated>
    <difficult>0</difficult>
    <bndbox>
      <xmin>390</xmin>
      <ymin>110</ymin>
      <xmax>680</xmax>
      <ymax>265</ymax>
    </bndbox>
  </object>
  <object>
    <name>fire</name>
    <pose>Unspecified</pose>
    <truncated>0</truncated>
    <difficult>0</difficult>
    <bndbox>
      <xmin>727</xmin>
      <ymin>111</ymin>
      <xmax>983</xmax>
      <ymax>273</ymax>
    </bndbox>
  </object>
</annotation>
